pyreedsolomon/__init__.py
pyreedsolomon/pyreedsolomon.py
pyreedsolomon-1.0.3.dist-info/LICENSE
pyreedsolomon-1.0.3.dist-info/METADATA
pyreedsolomon-1.0.3.dist-info/WHEEL
pyreedsolomon-1.0.3.dist-info/top_level.txt
pyreedsolomon-1.0.3.dist-info/RECORD
