Metadata-Version: 2.1
Name: pyreedsolomon
Version: 1.0.3
Summary: Fast python interface to the linux kernel reed solomon libraries
Home-page: https://github.com/mugpahug/pyreedsolomon
Author: Edwin G. W. Peters
Author-email: edwin.g.w.peters@gmail.com
License: GPL3
Keywords: reed solomon reed-solomon reedsolomon forward error correction
Platform: UNKNOWN
Classifier: Development Status :: 4 - Beta
Classifier: Intended Audience :: Developers
Classifier: Topic :: Software Development :: Libraries
Classifier: License :: OSI Approved :: GNU General Public License v3 or later (GPLv3+)
Classifier: Programming Language :: Python :: 3
Classifier: Programming Language :: Python :: 3.5
Requires-Dist: numpy
